googlesheettranslate/Err.py
googlesheettranslate/__init__.py
googlesheettranslate/main.py
googlesheettranslate/Readers/Err.py
googlesheettranslate/Readers/__init__.py
googlesheettranslate/Readers/__pycache__/Err.cpython-38.pyc
googlesheettranslate/Readers/__pycache__/__init__.cpython-38.pyc
googlesheettranslate/Readers/transformers/Android.py
googlesheettranslate/Readers/transformers/Jsi18n.py
googlesheettranslate/Readers/transformers/PyLan.py
googlesheettranslate/Readers/transformers/__init__.py
googlesheettranslate/Readers/transformers/corehelper.py
googlesheettranslate/Readers/transformers/itransformer.py
googlesheettranslate/Readers/transformers/__pycache__/Android.cpython-38.pyc
googlesheettranslate/Readers/transformers/__pycache__/Jsi18n.cpython-38.pyc
googlesheettranslate/Readers/transformers/__pycache__/PyLan.cpython-38.pyc
googlesheettranslate/Readers/transformers/__pycache__/__init__.cpython-38.pyc
googlesheettranslate/Readers/transformers/__pycache__/corehelper.cpython-38.pyc
googlesheettranslate/Readers/transformers/__pycache__/itransformer.cpython-38.pyc
googlesheettranslate/__pycache__/__init__.cpython-38.pyc
googlesheettranslate/__pycache__/main.cpython-38.pyc
googlesheettranslate/googlesheettech/Common.py
googlesheettranslate/googlesheettech/__init__.py
googlesheettranslate/googlesheettech/main.py
googlesheettranslate/googlesheettech/__pycache__/Common.cpython-38.pyc
googlesheettranslate/googlesheettech/__pycache__/__init__.cpython-38.pyc
googlesheettranslate/googlesheettech/__pycache__/main.cpython-38.pyc
googlesheettranslate/googlesheettech/cartrige/Android.py
googlesheettranslate/googlesheettech/cartrige/IOS.py
googlesheettranslate/googlesheettech/cartrige/__init__.py
googlesheettranslate/googlesheettech/cartrige/__pycache__/Android.cpython-38.pyc
googlesheettranslate/googlesheettech/cartrige/__pycache__/IOS.cpython-38.pyc
googlesheettranslate/googlesheettech/cartrige/__pycache__/__init__.cpython-38.pyc
googlesheettranslate-2.11.35.dist-info/METADATA
googlesheettranslate-2.11.35.dist-info/WHEEL
googlesheettranslate-2.11.35.dist-info/top_level.txt
googlesheettranslate-2.11.35.dist-info/RECORD
