Metadata-Version: 2.1
Name: googlesheettranslate
Version: 2.11.35
Summary: Non credential proved url scrapper for google sheet
Home-page: https://gitee.com/jjhoc/sheet-localization-py
Author: Shodan Vault & Heskemo
Author-email: steein.shamsudin@gmail.com
License: MIT License
Keywords: google sheet cli sdk
Platform: UNKNOWN
Classifier: Development Status :: 3 - Alpha
Classifier: Intended Audience :: Developers
Classifier: License :: OSI Approved :: MIT License
Classifier: Natural Language :: English
Classifier: Programming Language :: Python :: 3
Classifier: Programming Language :: Python :: 3.6
Classifier: Programming Language :: Python :: 3.7
Classifier: Programming Language :: Python :: 3.8
Classifier: Programming Language :: Python :: 3.9
Requires-Python: >=3.5,<=4
Requires-Dist: bs4
Requires-Dist: requests (<3.0.0,>=2.16.0)
Requires-Dist: base58
Requires-Dist: attrdict
Provides-Extra: dev
Requires-Dist: coverage ; extra == 'dev'
Requires-Dist: pep8 ; extra == 'dev'
Requires-Dist: pyflakes ; extra == 'dev'
Requires-Dist: pylint ; extra == 'dev'
Requires-Dist: pytest-cov ; extra == 'dev'
Requires-Dist: mock ; extra == 'dev'
Requires-Dist: sphinx-better-theme (>=0.1.4) ; extra == 'dev'
Requires-Dist: click (>=5.1) ; extra == 'dev'
Requires-Dist: configparser (==3.5.0) ; extra == 'dev'
Requires-Dist: contextlib2 (>=0.5.4) ; extra == 'dev'
Requires-Dist: py-solc (>=0.4.0) ; extra == 'dev'
Requires-Dist: pytest (>=2.7.2) ; extra == 'dev'
Requires-Dist: sphinx ; extra == 'dev'
Requires-Dist: pdoc3 ; extra == 'dev'
Requires-Dist: sphinx-rtd-theme (>=0.1.9) ; extra == 'dev'
Requires-Dist: toposort (>=1.4) ; extra == 'dev'
Requires-Dist: urllib3 ; extra == 'dev'
Requires-Dist: wheel (>=0.31.0) ; extra == 'dev'
Requires-Dist: bumpversion ; extra == 'dev'
Requires-Dist: flaky (>=3.3.0) ; extra == 'dev'
Requires-Dist: hypothesis (>=3.31.2) ; extra == 'dev'
Requires-Dist: pytest (<4,>=3.5.0) ; extra == 'dev'
Requires-Dist: pytest-mock (==1.*) ; extra == 'dev'
Requires-Dist: pytest-pythonpath (>=0.3) ; extra == 'dev'
Requires-Dist: pytest-watch (==4.*) ; extra == 'dev'
Requires-Dist: pytest-xdist (==1.*) ; extra == 'dev'
Requires-Dist: setuptools (>=38.6.0) ; extra == 'dev'
Requires-Dist: tox (>=1.8.0) ; extra == 'dev'
Requires-Dist: twine (>=1.11.0) ; extra == 'dev'
Requires-Dist: tqdm ; extra == 'dev'
Requires-Dist: when-changed ; extra == 'dev'
Provides-Extra: docs
Requires-Dist: mock ; extra == 'docs'
Requires-Dist: sphinx-better-theme (>=0.1.4) ; extra == 'docs'
Requires-Dist: click (>=5.1) ; extra == 'docs'
Requires-Dist: configparser (==3.5.0) ; extra == 'docs'
Requires-Dist: contextlib2 (>=0.5.4) ; extra == 'docs'
Requires-Dist: py-solc (>=0.4.0) ; extra == 'docs'
Requires-Dist: pytest (>=2.7.2) ; extra == 'docs'
Requires-Dist: sphinx ; extra == 'docs'
Requires-Dist: pdoc3 ; extra == 'docs'
Requires-Dist: sphinx-rtd-theme (>=0.1.9) ; extra == 'docs'
Requires-Dist: toposort (>=1.4) ; extra == 'docs'
Requires-Dist: urllib3 ; extra == 'docs'
Requires-Dist: wheel (>=0.31.0) ; extra == 'docs'
Provides-Extra: tester
Requires-Dist: coverage ; extra == 'tester'
Requires-Dist: pep8 ; extra == 'tester'
Requires-Dist: pyflakes ; extra == 'tester'
Requires-Dist: pylint ; extra == 'tester'
Requires-Dist: pytest-cov ; extra == 'tester'
